mgraph_ai_service_cache/__init__.py
mgraph_ai_service_cache/config.py
mgraph_ai_service_cache/fast_api/Cache_Service__Fast_API.py
mgraph_ai_service_cache/fast_api/__init__.py
mgraph_ai_service_cache/fast_api/lambda_handler.py
mgraph_ai_service_cache/fast_api/routes/Routes__Info.py
mgraph_ai_service_cache/fast_api/routes/Routes__Namespace.py
mgraph_ai_service_cache/fast_api/routes/Routes__Namespaces.py
mgraph_ai_service_cache/fast_api/routes/Routes__Server.py
mgraph_ai_service_cache/fast_api/routes/__init__.py
mgraph_ai_service_cache/fast_api/routes/admin/Routes__Admin__Storage.py
mgraph_ai_service_cache/fast_api/routes/data/Routes__Data__Delete.py
mgraph_ai_service_cache/fast_api/routes/data/Routes__Data__Exists.py
mgraph_ai_service_cache/fast_api/routes/data/Routes__Data__List.py
mgraph_ai_service_cache/fast_api/routes/data/Routes__Data__Retrieve.py
mgraph_ai_service_cache/fast_api/routes/data/Routes__Data__Store.py
mgraph_ai_service_cache/fast_api/routes/data/Routes__Data__Update.py
mgraph_ai_service_cache/fast_api/routes/file/Routes__File__Delete.py
mgraph_ai_service_cache/fast_api/routes/file/Routes__File__Exists.py
mgraph_ai_service_cache/fast_api/routes/file/Routes__File__Retrieve.py
mgraph_ai_service_cache/fast_api/routes/file/Routes__File__Store.py
mgraph_ai_service_cache/fast_api/routes/file/Routes__File__Update.py
mgraph_ai_service_cache/fast_api/routes/test_data/Routes__Test_Data.py
mgraph_ai_service_cache/fast_api/routes/zip/Routes__Zip.py
mgraph_ai_service_cache/schemas/service/cache_service/Schema__Store__Context.py
mgraph_ai_service_cache/schemas/test_data/Schema__Test_Data.py
mgraph_ai_service_cache/service/__init__.py
mgraph_ai_service_cache/service/cache/Cache__Config.py
mgraph_ai_service_cache/service/cache/Cache__Handler.py
mgraph_ai_service_cache/service/cache/Cache__Hash__Config.py
mgraph_ai_service_cache/service/cache/Cache__Service.py
mgraph_ai_service_cache/service/cache/__init__.py
mgraph_ai_service_cache-0.11.0.dist-info/LICENSE
mgraph_ai_service_cache-0.11.0.dist-info/METADATA
mgraph_ai_service_cache-0.11.0.dist-info/WHEEL
mgraph_ai_service_cache-0.11.0.dist-info/RECORD
