Metadata-Version: 2.1
Name: mgraph_ai_service_cache
Version: 0.11.0
Summary: MGraph-AI__Service__Cache
Home-page: https://github.com/the-cyber-boardroom/MGraph-AI__Service__Cache
License: Apache 2.0
Author: Dinis Cruz
Author-email: dinis.cruz@owasp.org
Requires-Python: >=3.12,<4.0
Classifier: License :: Other/Proprietary License
Classifier: Programming Language :: Python :: 3
Classifier: Programming Language :: Python :: 3.12
Requires-Dist: memory_fs
Requires-Dist: mgraph-ai-service-cache-client
Requires-Dist: osbot-fast-api-serverless
Project-URL: Repository, https://github.com/the-cyber-boardroom/MGraph-AI__Service__Cache
